spychart/__init__.py
spychart/control_rules.py
spychart/core.py
spychart/helpers.py
spychart/spc_functions.py
spychart/spc_plots.py
tests/__init__.py
tests/test_control_rules.py
tests/test_core.py
tests/test_helpers.py
tests/test_process_functions.py
spychart-1.0.0.dist-info/LICENSE.txt
spychart-1.0.0.dist-info/METADATA
spychart-1.0.0.dist-info/WHEEL
spychart-1.0.0.dist-info/top_level.txt
spychart-1.0.0.dist-info/RECORD
