Metadata-Version: 2.1
Name: spychart
Version: 1.0.0
Summary: A Python library for Statistical Process Control (SPC) analytics.
Author-email: Ben Holdsworth <Benjamin.Holdsworth@somersetft.nhs.uk>, SFT Data Science <Data.Science@somersetft.nhs.uk>
Project-URL: Homepage, https://github.com/Somerset-NHS-FT-DS-Improvement/spyc
Project-URL: Issues, https://github.com/Somerset-NHS-FT-DS-Improvement/spyc/issues
Classifier: Programming Language :: Python :: 3
Classifier: Operating System :: OS Independent
Requires-Python: >=3.10
License-File: LICENSE.txt
Requires-Dist: numpy>=1.26.4
Requires-Dist: pandas>=2.2.3
Requires-Dist: plotly>=5.24.1
Requires-Dist: seaborn>=0.13.2
Requires-Dist: matplotlib>=3.10.0
Provides-Extra: dev
Requires-Dist: pytest>=7.4.0; extra == "dev"
Requires-Dist: black>=24.2.0; extra == "dev"
Requires-Dist: isort>=5.13.2; extra == "dev"
